{
  "slug": "citroen-e-c4",
  "brand": "Citroën",
  "model": "ë-C4 & ë-C4 X",
  "variant": "50 / 54 kWh",
  "bodyType": "Berline compacte",
  "segment": "C",
  "productionCountry": "Espagne",
  "assemblyPlant": "Madrid",
  "releaseYear": 2020,
  "marketAvailability": "Disponible",
  "power_kW": 115,
  "power_hp": 156,
  "torque_Nm": 260,
  "drivetrain": "FWD",
  "motors": 1,
  "acceleration_0_100_s": 9.2,
  "topSpeed_kmh": 150,
  "usableCapacity_kWh": 50.8,
  "grossCapacity_kWh": 54,
  "chemistry": "NMC",
  "architecture_V": 400,
  "mass_kg": 1560,
  "wltp_max_km": 420,
  "wltp_min_km": 350,
  "realRange": {
    "mixed_km": 330,
    "highway_130_km": 220,
    "urban_km": 400,
    "winter_minus5_km": 260,
    "confidence": "tested"
  },
  "consumption_mixed_kWh_per_100km": 15,
  "consumption_highway_kWh_per_100km": 21,
  "consumption_winter_kWh_per_100km": 19,
  "dragCoefficient_Cx": 0.29,
  "chargingDC": {
    "peakPower_kW": 100,
    "time_10_80_min": 30,
    "kWh_added_30min": 38,
    "confidence": "tested"
  },
  "chargingAC": {
    "onboardCharger_kW": 11,
    "phases": 3,
    "time_0_100_h": 5.5
  },
  "plugAndCharge": false,
  "v2l": false,
  "v2g": false,
  "v2l_option_EUR": null,
  "chargingCurve": [
    {
      "soc": 0,
      "power": 77
    },
    {
      "soc": 10,
      "power": 100
    },
    {
      "soc": 50,
      "power": 77
    },
    {
      "soc": 80,
      "power": 38
    },
    {
      "soc": 100,
      "power": 8
    }
  ],
  "rangeTests": [],
  "thousandKmChallenge": null,
  "length_mm": 4360,
  "width_mm": 1800,
  "height_mm": 1525,
  "wheelbase_mm": 2670,
  "trunkCapacity_L": 380,
  "trunkCapacityFolded_L": 1250,
  "frunkCapacity_L": null,
  "trims": [
    {
      "name": "ë-C4 You 136 ch",
      "price_EUR": 33850,
      "batteryUsed": "50 kWh",
      "equipmentHighlights": [
        "Moteur 136 ch - Batterie 50 kWh",
        "Climatisation automatique bi-zone",
        "Suspensions Advanced Comfort"
      ]
    },
    {
      "name": "ë-C4 Plus 136 ch",
      "price_EUR": 34800,
      "batteryUsed": "50 kWh",
      "equipmentHighlights": [
        "Caméra de recul",
        "Jantes alliage 18 pouces",
        "Rétroviseurs rabattables électriquement"
      ]
    },
    {
      "name": "ë-C4 Plus 156 ch",
      "price_EUR": 35950,
      "batteryUsed": "54 kWh",
      "equipmentHighlights": [
        "Moteur 156 ch - Batterie 54 kWh",
        "Écran tactile 10 pouces",
        "Citroën Connect Box"
      ]
    },
    {
      "name": "ë-C4 Max 156 ch",
      "price_EUR": 38150,
      "batteryUsed": "54 kWh",
      "equipmentHighlights": [
        "Accès et démarrage mains libres",
        "Navigation connectée 3D",
        "Affichage tête haute couleur"
      ]
    },
    {
      "name": "ë-C4 X You 136 ch",
      "price_EUR": 34450,
      "batteryUsed": "50 kWh",
      "equipmentHighlights": [
        "Profil silhouette Fastback",
        "Volume coffre 510 L",
        "Suspensions Advanced Comfort"
      ]
    },
    {
      "name": "ë-C4 X Plus 136 ch",
      "price_EUR": 35400,
      "batteryUsed": "50 kWh",
      "equipmentHighlights": [
        "Caméra de recul 180°",
        "Jantes alliage 18 pouces",
        "My Citroën Play"
      ]
    },
    {
      "name": "ë-C4 X Plus 156 ch",
      "price_EUR": 36550,
      "batteryUsed": "54 kWh",
      "equipmentHighlights": [
        "Moteur 156 ch - Batterie 54 kWh",
        "Autonomie étendue 420 km",
        "Aide au stationnement arrière"
      ]
    },
    {
      "name": "ë-C4 X Max 156 ch",
      "price_EUR": 38850,
      "batteryUsed": "54 kWh",
      "equipmentHighlights": [
        "Système My Citroën Drive Plus",
        "Sièges Advanced Comfort Alcantara",
        "Surveillance des angles morts"
      ]
    }
  ],
  "leasingSocialEligible": false,
  "leasingSocial_EUR_per_month": null,
  "availableAids": [
    {
      "label": "Prime CEE",
      "amount_EUR": 6500,
      "conditions": "Socle de base de la Prime CEE 2026 pour véhicule éligible à l'éco-score ADEME."
    },
    {
      "label": "Majoration Batterie Européenne",
      "amount_EUR": 2000,
      "conditions": "Majoration pour batterie fabriquée en Europe."
    }
  ],
  "configurations": [
    {
      "id": "citroen-e-c4-you-136",
      "label": "ë-C4 You · 136 ch",
      "battery": "standard",
      "trim": "ë-C4 You 136 ch",
      "wheelSize_inches": 18,
      "tyreType": "summer",
      "options": [],
      "price_EUR": 33850,
      "monthlyLease_EUR": 129,
      "leasingSocialEligible": false,
      "wltp_km": 350,
      "wltp_consumption_kWh_100km": 15,
      "realRange": {
        "mixed_km": 280,
        "highway_130_km": 185,
        "urban_km": 340,
        "winter_minus5_km": 220,
        "confidence": "estimated"
      },
      "rangeTests": [],
      "chargingDC_peak_kW": 100,
      "chargingDC_10_80_min": 30,
      "chargingDC_kWh_30min": 32,
      "chargingCurve": null,
      "availability": "available",
      "notes": "Version d'entrée de gamme berline"
    },
    {
      "id": "citroen-e-c4-plus-136",
      "label": "ë-C4 Plus · 136 ch",
      "battery": "standard",
      "trim": "ë-C4 Plus 136 ch",
      "wheelSize_inches": 18,
      "tyreType": "summer",
      "options": [],
      "price_EUR": 34800,
      "monthlyLease_EUR": 149,
      "leasingSocialEligible": false,
      "wltp_km": 350,
      "wltp_consumption_kWh_100km": 15,
      "realRange": {
        "mixed_km": 280,
        "highway_130_km": 185,
        "urban_km": 340,
        "winter_minus5_km": 220,
        "confidence": "estimated"
      },
      "rangeTests": [],
      "chargingDC_peak_kW": 100,
      "chargingDC_10_80_min": 30,
      "chargingDC_kWh_30min": 32,
      "chargingCurve": null,
      "availability": "available",
      "notes": "Version cœur de gamme berline 136 ch"
    },
    {
      "id": "citroen-e-c4-plus-156",
      "label": "ë-C4 Plus · 156 ch",
      "battery": "standard",
      "trim": "ë-C4 Plus 156 ch",
      "wheelSize_inches": 18,
      "tyreType": "summer",
      "options": [],
      "price_EUR": 35950,
      "monthlyLease_EUR": 169,
      "leasingSocialEligible": false,
      "wltp_km": 420,
      "wltp_consumption_kWh_100km": 15,
      "realRange": {
        "mixed_km": 330,
        "highway_130_km": 220,
        "urban_km": 400,
        "winter_minus5_km": 260,
        "confidence": "tested"
      },
      "rangeTests": [],
      "chargingDC_peak_kW": 100,
      "chargingDC_10_80_min": 30,
      "chargingDC_kWh_30min": 38,
      "chargingCurve": null,
      "availability": "available",
      "notes": "Version cœur de gamme berline 156 ch"
    },
    {
      "id": "citroen-e-c4-max-156",
      "label": "ë-C4 Max · 156 ch",
      "battery": "standard",
      "trim": "ë-C4 Max 156 ch",
      "wheelSize_inches": 18,
      "tyreType": "summer",
      "options": [],
      "price_EUR": 38150,
      "monthlyLease_EUR": 199,
      "leasingSocialEligible": false,
      "wltp_km": 420,
      "wltp_consumption_kWh_100km": 15.2,
      "realRange": {
        "mixed_km": 325,
        "highway_130_km": 215,
        "urban_km": 395,
        "winter_minus5_km": 255,
        "confidence": "tested"
      },
      "rangeTests": [],
      "chargingDC_peak_kW": 100,
      "chargingDC_10_80_min": 30,
      "chargingDC_kWh_30min": 38,
      "chargingCurve": null,
      "availability": "available",
      "notes": "Version haut de gamme berline 156 ch"
    },
    {
      "id": "citroen-e-c4-x-you-136",
      "label": "ë-C4 X You · 136 ch",
      "battery": "standard",
      "trim": "ë-C4 X You 136 ch",
      "wheelSize_inches": 18,
      "tyreType": "summer",
      "options": [],
      "price_EUR": 34450,
      "monthlyLease_EUR": 139,
      "leasingSocialEligible": false,
      "wltp_km": 360,
      "wltp_consumption_kWh_100km": 14.8,
      "realRange": {
        "mixed_km": 290,
        "highway_130_km": 190,
        "urban_km": 350,
        "winter_minus5_km": 230,
        "confidence": "estimated"
      },
      "rangeTests": [],
      "chargingDC_peak_kW": 100,
      "chargingDC_10_80_min": 30,
      "chargingDC_kWh_30min": 32,
      "chargingCurve": null,
      "availability": "available",
      "notes": "Silhouette tri-corps Fastback entrée de gamme"
    },
    {
      "id": "citroen-e-c4-x-plus-136",
      "label": "ë-C4 X Plus · 136 ch",
      "battery": "standard",
      "trim": "ë-C4 X Plus 136 ch",
      "wheelSize_inches": 18,
      "tyreType": "summer",
      "options": [],
      "price_EUR": 35400,
      "monthlyLease_EUR": 159,
      "leasingSocialEligible": false,
      "wltp_km": 360,
      "wltp_consumption_kWh_100km": 14.8,
      "realRange": {
        "mixed_km": 290,
        "highway_130_km": 190,
        "urban_km": 350,
        "winter_minus5_km": 230,
        "confidence": "estimated"
      },
      "rangeTests": [],
      "chargingDC_peak_kW": 100,
      "chargingDC_10_80_min": 30,
      "chargingDC_kWh_30min": 32,
      "chargingCurve": null,
      "availability": "available",
      "notes": "Silhouette tri-corps Fastback cœur de gamme 136 ch"
    },
    {
      "id": "citroen-e-c4-x-plus-156",
      "label": "ë-C4 X Plus · 156 ch",
      "battery": "standard",
      "trim": "ë-C4 X Plus 156 ch",
      "wheelSize_inches": 18,
      "tyreType": "summer",
      "options": [],
      "price_EUR": 36550,
      "monthlyLease_EUR": 179,
      "leasingSocialEligible": false,
      "wltp_km": 420,
      "wltp_consumption_kWh_100km": 14.9,
      "realRange": {
        "mixed_km": 335,
        "highway_130_km": 225,
        "urban_km": 405,
        "winter_minus5_km": 265,
        "confidence": "estimated"
      },
      "rangeTests": [],
      "chargingDC_peak_kW": 100,
      "chargingDC_10_80_min": 30,
      "chargingDC_kWh_30min": 38,
      "chargingCurve": null,
      "availability": "available",
      "notes": "Silhouette tri-corps Fastback cœur de gamme 156 ch"
    },
    {
      "id": "citroen-e-c4-x-max-156",
      "label": "ë-C4 X Max · 156 ch",
      "battery": "standard",
      "trim": "ë-C4 X Max 156 ch",
      "wheelSize_inches": 18,
      "tyreType": "summer",
      "options": [],
      "price_EUR": 38850,
      "monthlyLease_EUR": 209,
      "leasingSocialEligible": false,
      "wltp_km": 420,
      "wltp_consumption_kWh_100km": 15.1,
      "realRange": {
        "mixed_km": 330,
        "highway_130_km": 220,
        "urban_km": 400,
        "winter_minus5_km": 260,
        "confidence": "estimated"
      },
      "rangeTests": [],
      "chargingDC_peak_kW": 100,
      "chargingDC_10_80_min": 30,
      "chargingDC_kWh_30min": 38,
      "chargingCurve": null,
      "availability": "available",
      "notes": "Silhouette tri-corps Fastback haut de gamme"
    }
  ],
  "warranty": {
    "vehicle_years": 5,
    "vehicle_km": 100000,
    "battery_years": 8,
    "battery_km": 160000,
    "battery_soh_minimum_percent": 70
  },
  "keyFeatures": [
    {
      "category": "confort",
      "label": "Confort Citroën légendaire avec butées hydrauliques progressives"
    },
    {
      "category": "technologie",
      "label": "Interface My Citroën Drive Plus avec écran HD 10 pouces"
    },
    {
      "category": "securite",
      "label": "Régulateur de vitesse adaptatif et Highway Driver Assist"
    },
    {
      "category": "design",
      "label": "Silhouette aérodynamique et signature lumineuse LED en V"
    }
  ],
  "verdict": {
    "strengths": [
      "Confort exceptionnel des suspensions et des sièges",
      "Rapport prix/équipements très attractif sur le segment C"
    ],
    "weaknesses": [
      "Vitesse de recharge limitée à 100 kW",
      "Espace à la tête à l'arrière légèrement contraint par le toit fuyant"
    ],
    "idealUserProfile": "Conducteurs recherchant le confort absolu pour les trajets quotidiens et périurbains avec un tarif contenu.",
    "notIdealFor": "Grands voyageurs autoroutiers ayant besoin de charges ultra-rapides régulières."
  },
  "lastUpdated": "2026-06-04",
  "sources": [
    "citroen-fr",
    "automobile-propre"
  ],
  "imageCredit": "Constructeur"
}