{
  "slug": "kia-ev4",
  "brand": "Kia",
  "model": "EV4",
  "variant": "Berline compacte électrique",
  "bodyType": "Hatchback 5 portes",
  "segment": "C, berline compacte",
  "productionCountry": "Slovaquie",
  "assemblyPlant": "Žilina (usine 100 % électricité renouvelable)",
  "releaseYear": 2026,
  "marketAvailability": "Commandes ouvertes en France, livraisons à partir du T1 2026",
  "power_kW": 150,
  "power_hp": 204,
  "torque_Nm": 283,
  "drivetrain": "FWD",
  "motors": 1,
  "acceleration_0_100_s": 7.4,
  "topSpeed_kmh": 170,
  "usableCapacity_kWh": 81.4,
  "grossCapacity_kWh": 84.6,
  "chemistry": "NMC",
  "architecture_V": 400,
  "mass_kg": 1850,
  "wltp_max_km": 625,
  "wltp_min_km": 410,
  "realRange": {
    "mixed_km": 490,
    "highway_130_km": 368,
    "urban_km": 555,
    "winter_minus5_km": 400,
    "confidence": "tested"
  },
  "consumption_mixed_kWh_per_100km": 15.8,
  "consumption_highway_kWh_per_100km": 22.1,
  "consumption_winter_kWh_per_100km": 20.4,
  "dragCoefficient_Cx": 0.23,
  "chargingDC": {
    "peakPower_kW": 128,
    "time_10_80_min": 31,
    "kWh_added_30min": 57,
    "confidence": "tested"
  },
  "chargingAC": {
    "onboardCharger_kW": 11,
    "phases": 3,
    "time_0_100_h": 7.25
  },
  "plugAndCharge": true,
  "v2l": true,
  "v2g": false,
  "v2l_option_EUR": 1550,
  "chargingCurve": [
    {
      "soc": 0,
      "power": 110
    },
    {
      "soc": 5,
      "power": 120
    },
    {
      "soc": 10,
      "power": 128
    },
    {
      "soc": 20,
      "power": 128
    },
    {
      "soc": 30,
      "power": 125
    },
    {
      "soc": 40,
      "power": 118
    },
    {
      "soc": 50,
      "power": 110
    },
    {
      "soc": 60,
      "power": 95
    },
    {
      "soc": 70,
      "power": 78
    },
    {
      "soc": 80,
      "power": 58
    },
    {
      "soc": 90,
      "power": 36
    },
    {
      "soc": 100,
      "power": 14
    }
  ],
  "rangeTests": [
    {
      "sourceId": "nyland",
      "testDate": "2026-04",
      "speed_kmh": 90,
      "range_km": null,
      "consumption_kWh_100km": 14.1,
      "temperature_C": null,
      "wheelSize_inches": 19,
      "tyreModel": null,
      "protocol": "nyland",
      "videoUrl": "https://www.youtube.com/watch?v=w_3W15PT9Z4",
      "notes": "Version GT-Line avec jantes 19 pouces. Résultats relayés par InsideEVs DE."
    },
    {
      "sourceId": "nyland",
      "testDate": "2026-04",
      "speed_kmh": 120,
      "range_km": null,
      "consumption_kWh_100km": 20.4,
      "temperature_C": null,
      "wheelSize_inches": 19,
      "tyreModel": null,
      "protocol": "nyland",
      "videoUrl": "https://www.youtube.com/watch?v=w_3W15PT9Z4",
      "notes": "Estimation de range basée sur la capacité batterie utile (~81 kWh) et la conso mesurée."
    },
    {
      "sourceId": "automobile-propre",
      "testDate": "2026-03",
      "speed_kmh": 130,
      "range_km": 368,
      "consumption_kWh_100km": 22.1,
      "temperature_C": 13,
      "wheelSize_inches": 19,
      "tyreModel": "Michelin Primacy 5 Energy 215/50 R19",
      "protocol": "tested-other",
      "videoUrl": null,
      "notes": "Trajet autoroutier réel entre Lyon et Paris, conditions printanières."
    },
    {
      "sourceId": "automobile-propre",
      "testDate": "2026-03",
      "speed_kmh": 100,
      "range_km": 493,
      "consumption_kWh_100km": 16.5,
      "temperature_C": 13,
      "wheelSize_inches": 19,
      "tyreModel": "Michelin Primacy 5 Energy 215/50 R19",
      "protocol": "tested-other",
      "videoUrl": null,
      "notes": "Cycle mixte sur parcours de 100 km."
    },
    {
      "sourceId": "caradisiac",
      "testDate": "2026-01",
      "speed_kmh": null,
      "range_km": 350,
      "consumption_kWh_100km": 16.9,
      "temperature_C": null,
      "wheelSize_inches": 17,
      "tyreModel": null,
      "protocol": "tested-other",
      "videoUrl": null,
      "notes": "Standard 58 kWh, conso moyenne mesurée sur essai mixte."
    },
    {
      "sourceId": "actua-auto",
      "testDate": "2026",
      "speed_kmh": null,
      "range_km": 380,
      "consumption_kWh_100km": 15.2,
      "temperature_C": null,
      "wheelSize_inches": 17,
      "tyreModel": null,
      "protocol": "tested-other",
      "videoUrl": null,
      "notes": "Standard 58 kWh, parcours 250 km urbain et périurbain."
    },
    {
      "sourceId": "touring",
      "testDate": "2025-12",
      "speed_kmh": null,
      "range_km": null,
      "consumption_kWh_100km": 15.8,
      "temperature_C": 8,
      "wheelSize_inches": 17,
      "tyreModel": null,
      "protocol": "tested-other",
      "videoUrl": null,
      "notes": "Standard 58 kWh, essai hivernal modéré en Belgique, parcours mixte."
    }
  ],
  "thousandKmChallenge": {
    "sourceId": "nyland",
    "totalTime_minutes": null,
    "averageSpeed_kmh": null,
    "averageConsumption_Wh_km": null,
    "chargingStops": null,
    "averageTemperature_C": null,
    "testDate": "2026-04",
    "videoUrl": "https://www.youtube.com/watch?v=w_3W15PT9Z4",
    "confidence": "pending"
  },
  "length_mm": 4430,
  "width_mm": 1860,
  "height_mm": 1480,
  "wheelbase_mm": 2820,
  "trunkCapacity_L": 435,
  "trunkCapacityFolded_L": 1415,
  "frunkCapacity_L": null,
  "trims": [
    {
      "name": "Air",
      "price_EUR": 38290,
      "batteryUsed": "58,3 kWh",
      "equipmentHighlights": [
        "Jantes 17\" aérodynamiques",
        "Double écran 12,3\" + 5\"",
        "Climatisation automatique mono-zone",
        "Régulateur adaptatif intelligent (NSCC)",
        "Caméra de recul"
      ]
    },
    {
      "name": "Earth",
      "price_EUR": 40590,
      "batteryUsed": "58,3 kWh",
      "equipmentHighlights": [
        "Jantes 17\" diamantées",
        "Sièges chauffants conducteur + passager",
        "Volant chauffant",
        "Système audio Harman Kardon 8 HP",
        "Toit ouvrant panoramique"
      ]
    },
    {
      "name": "Air",
      "price_EUR": 42890,
      "batteryUsed": "81,4 kWh",
      "equipmentHighlights": [
        "Jantes 17\" aérodynamiques",
        "Double écran 12,3\" + 5\"",
        "Pompe à chaleur incluse",
        "Régulateur adaptatif intelligent (NSCC)",
        "Caméra de recul"
      ]
    },
    {
      "name": "Earth",
      "price_EUR": 45190,
      "batteryUsed": "81,4 kWh",
      "equipmentHighlights": [
        "Jantes 17\" diamantées",
        "Sièges chauffants conducteur + passager",
        "Volant chauffant",
        "Système audio Harman Kardon 8 HP",
        "Toit ouvrant panoramique"
      ]
    },
    {
      "name": "GT-Line",
      "price_EUR": 46990,
      "batteryUsed": "81,4 kWh",
      "equipmentHighlights": [
        "Jantes 19\" GT-Line",
        "Sièges sport ergonomiques avec ventilation",
        "Suspension à amortissement piloté",
        "Pédalier alu et aileron arrière",
        "Affichage tête haute couleur"
      ]
    }
  ],
  "leasingSocialEligible": true,
  "leasingSocial_EUR_per_month": 189,
  "availableAids": [
    {
      "label": "Prime CEE VE",
      "amount_EUR": 8100
    }
  ],
  "configurations": [
    {
      "id": "std-air-17",
      "label": "Standard · Air · 17\"",
      "battery": "standard",
      "trim": "Air",
      "wheelSize_inches": 17,
      "tyreType": "summer",
      "options": [],
      "price_EUR": 38290,
      "monthlyLease_EUR": 189,
      "leasingSocialEligible": true,
      "wltp_km": 440,
      "wltp_consumption_kWh_100km": 14.4,
      "realRange": {
        "mixed_km": 380,
        "highway_130_km": 265,
        "urban_km": 430,
        "winter_minus5_km": 300,
        "confidence": "tested"
      },
      "rangeTests": [
        {
          "sourceId": "caradisiac",
          "testDate": "2026-01",
          "speed_kmh": null,
          "range_km": 350,
          "consumption_kWh_100km": 16.9,
          "temperature_C": null,
          "wheelSize_inches": 17,
          "tyreModel": null,
          "protocol": "tested-other",
          "videoUrl": null,
          "notes": "Conso moyenne mesurée sur essai mixte, autonomie réelle estimée à 350 km."
        },
        {
          "sourceId": "actua-auto",
          "testDate": "2026",
          "speed_kmh": null,
          "range_km": 380,
          "consumption_kWh_100km": 15.2,
          "temperature_C": null,
          "wheelSize_inches": 17,
          "tyreModel": null,
          "protocol": "tested-other",
          "videoUrl": null,
          "notes": "Parcours 250 km urbain et périurbain."
        },
        {
          "sourceId": "touring",
          "testDate": "2025-12",
          "speed_kmh": null,
          "range_km": null,
          "consumption_kWh_100km": 15.8,
          "temperature_C": 8,
          "wheelSize_inches": 17,
          "tyreModel": null,
          "protocol": "tested-other",
          "videoUrl": null,
          "notes": "Essai hivernal modéré en Belgique, parcours mixte."
        }
      ],
      "chargingDC_peak_kW": 108,
      "chargingDC_10_80_min": 29,
      "chargingDC_kWh_30min": 41,
      "chargingCurve": [
        {
          "soc": 0,
          "power": 95
        },
        {
          "soc": 5,
          "power": 105
        },
        {
          "soc": 10,
          "power": 108
        },
        {
          "soc": 20,
          "power": 108
        },
        {
          "soc": 30,
          "power": 105
        },
        {
          "soc": 40,
          "power": 102
        },
        {
          "soc": 50,
          "power": 95
        },
        {
          "soc": 60,
          "power": 80
        },
        {
          "soc": 70,
          "power": 65
        },
        {
          "soc": 80,
          "power": 48
        },
        {
          "soc": 90,
          "power": 30
        },
        {
          "soc": 100,
          "power": 12
        }
      ],
      "availability": "available",
      "notes": "Éligible leasing social. Batterie 58,3 kWh utiles."
    },
    {
      "id": "std-earth-17",
      "label": "Standard · Earth · 17\"",
      "battery": "standard",
      "trim": "Earth",
      "wheelSize_inches": 17,
      "tyreType": "summer",
      "options": [],
      "price_EUR": 40590,
      "monthlyLease_EUR": null,
      "leasingSocialEligible": false,
      "wltp_km": 440,
      "wltp_consumption_kWh_100km": 14.4,
      "realRange": {
        "mixed_km": 380,
        "highway_130_km": 265,
        "urban_km": 430,
        "winter_minus5_km": 300,
        "confidence": "tested"
      },
      "rangeTests": [],
      "chargingDC_peak_kW": 108,
      "chargingDC_10_80_min": 29,
      "chargingDC_kWh_30min": 41,
      "chargingCurve": null,
      "availability": "available",
      "notes": "Mêmes performances que Air Standard, finition supérieure."
    },
    {
      "id": "lr-air-17",
      "label": "· Air · 17\"",
      "battery": "long-range",
      "trim": "Air",
      "wheelSize_inches": 17,
      "tyreType": "summer",
      "options": [],
      "price_EUR": 42890,
      "monthlyLease_EUR": null,
      "leasingSocialEligible": false,
      "wltp_km": 625,
      "wltp_consumption_kWh_100km": 14.8,
      "realRange": {
        "mixed_km": 510,
        "highway_130_km": 385,
        "urban_km": 580,
        "winter_minus5_km": 420,
        "confidence": "estimated"
      },
      "rangeTests": [],
      "chargingDC_peak_kW": 128,
      "chargingDC_10_80_min": 31,
      "chargingDC_kWh_30min": 57,
      "chargingCurve": [
        {
          "soc": 0,
          "power": 110
        },
        {
          "soc": 5,
          "power": 120
        },
        {
          "soc": 10,
          "power": 128
        },
        {
          "soc": 20,
          "power": 128
        },
        {
          "soc": 30,
          "power": 125
        },
        {
          "soc": 40,
          "power": 118
        },
        {
          "soc": 50,
          "power": 110
        },
        {
          "soc": 60,
          "power": 95
        },
        {
          "soc": 70,
          "power": 78
        },
        {
          "soc": 80,
          "power": 58
        },
        {
          "soc": 90,
          "power": 36
        },
        {
          "soc": 100,
          "power": 14
        }
      ],
      "availability": "available",
      "notes": "Long Range en jantes 17\", autonomie supérieure aux 19\". Pompe à chaleur de série."
    },
    {
      "id": "lr-earth-17",
      "label": "· Earth · 17\"",
      "battery": "long-range",
      "trim": "Earth",
      "wheelSize_inches": 17,
      "tyreType": "summer",
      "options": [],
      "price_EUR": 45190,
      "monthlyLease_EUR": null,
      "leasingSocialEligible": false,
      "wltp_km": 625,
      "wltp_consumption_kWh_100km": 14.8,
      "realRange": {
        "mixed_km": 510,
        "highway_130_km": 385,
        "urban_km": 580,
        "winter_minus5_km": 420,
        "confidence": "estimated"
      },
      "rangeTests": [],
      "chargingDC_peak_kW": 128,
      "chargingDC_10_80_min": 31,
      "chargingDC_kWh_30min": 57,
      "chargingCurve": null,
      "availability": "available",
      "notes": "Long Range Earth, mêmes performances que Air LR avec finition supérieure."
    },
    {
      "id": "lr-gt-line-19",
      "label": "· GT-Line · 19\"",
      "battery": "long-range",
      "trim": "GT-Line",
      "wheelSize_inches": 19,
      "tyreType": "summer",
      "options": [],
      "price_EUR": 46990,
      "monthlyLease_EUR": null,
      "leasingSocialEligible": false,
      "wltp_km": 584,
      "wltp_consumption_kWh_100km": 15.8,
      "realRange": {
        "mixed_km": 490,
        "highway_130_km": 368,
        "urban_km": 555,
        "winter_minus5_km": 400,
        "confidence": "tested"
      },
      "rangeTests": [
        {
          "sourceId": "nyland",
          "testDate": "2026-04",
          "speed_kmh": 90,
          "range_km": null,
          "consumption_kWh_100km": 14.1,
          "temperature_C": null,
          "wheelSize_inches": 19,
          "tyreModel": null,
          "protocol": "nyland",
          "videoUrl": "https://www.youtube.com/watch?v=w_3W15PT9Z4",
          "notes": "Version GT-Line avec jantes 19 pouces."
        },
        {
          "sourceId": "nyland",
          "testDate": "2026-04",
          "speed_kmh": 120,
          "range_km": null,
          "consumption_kWh_100km": 20.4,
          "temperature_C": null,
          "wheelSize_inches": 19,
          "tyreModel": null,
          "protocol": "nyland",
          "videoUrl": "https://www.youtube.com/watch?v=w_3W15PT9Z4",
          "notes": "Estimation de range basée sur la capacité batterie utile (~81 kWh) et la conso mesurée."
        },
        {
          "sourceId": "automobile-propre",
          "testDate": "2026-03",
          "speed_kmh": 130,
          "range_km": 368,
          "consumption_kWh_100km": 22.1,
          "temperature_C": 13,
          "wheelSize_inches": 19,
          "tyreModel": "Michelin Primacy 5 Energy 215/50 R19",
          "protocol": "tested-other",
          "videoUrl": null,
          "notes": "Trajet autoroutier réel entre Lyon et Paris, conditions printanières."
        },
        {
          "sourceId": "automobile-propre",
          "testDate": "2026-03",
          "speed_kmh": 100,
          "range_km": 493,
          "consumption_kWh_100km": 16.5,
          "temperature_C": 13,
          "wheelSize_inches": 19,
          "tyreModel": "Michelin Primacy 5 Energy 215/50 R19",
          "protocol": "tested-other",
          "videoUrl": null,
          "notes": "Cycle mixte sur parcours de 100 km."
        }
      ],
      "chargingDC_peak_kW": 128,
      "chargingDC_10_80_min": 31,
      "chargingDC_kWh_30min": 57,
      "chargingCurve": [
        {
          "soc": 0,
          "power": 110
        },
        {
          "soc": 5,
          "power": 120
        },
        {
          "soc": 10,
          "power": 128
        },
        {
          "soc": 20,
          "power": 128
        },
        {
          "soc": 30,
          "power": 125
        },
        {
          "soc": 40,
          "power": 118
        },
        {
          "soc": 50,
          "power": 110
        },
        {
          "soc": 60,
          "power": 95
        },
        {
          "soc": 70,
          "power": 78
        },
        {
          "soc": 80,
          "power": 58
        },
        {
          "soc": 90,
          "power": 36
        },
        {
          "soc": 100,
          "power": 14
        }
      ],
      "availability": "available",
      "notes": "Configuration testée par Nyland. Jantes 19\" = autonomie réduite vs 17\"."
    }
  ],
  "warranty": {
    "vehicle_years": 7,
    "vehicle_km": 150000,
    "battery_years": 8,
    "battery_km": 160000,
    "battery_soh_minimum_percent": 70
  },
  "keyFeatures": [
    {
      "category": "securite",
      "label": "Régulateur adaptatif avec maintien dans la voie (NSCC)"
    },
    {
      "category": "securite",
      "label": "Freinage d'urgence avec détection vélos / piétons"
    },
    {
      "category": "securite",
      "label": "Surveillance des angles morts active"
    },
    {
      "category": "technologie",
      "label": "Plug & Charge sur le réseau Ionity et IECharge"
    },
    {
      "category": "technologie",
      "label": "Connected Car Services 7 ans inclus"
    },
    {
      "category": "technologie",
      "label": "Mises à jour OTA infodivertissement et batterie"
    },
    {
      "category": "confort",
      "label": "Pompe à chaleur de série sur toutes les finitions Long Range"
    },
    {
      "category": "confort",
      "label": "Coffre 435 L à seuil bas, sous-coffre dédié aux câbles"
    },
    {
      "category": "design",
      "label": "Cx record du segment à 0,23"
    },
    {
      "category": "design",
      "label": "Finition GT-Line exclusive avec amortissement piloté"
    }
  ],
  "verdict": {
    "strengths": [
      "Autonomie réelle ~490 km en mixte (Long Range GT-Line), top du segment compact",
      "Éligible leasing social à 189 €/mois en Standard Air, quasi-unique sur ce niveau de prestation",
      "Recharge rapide ajoute 57 kWh en 30 min (Long Range), 41 kWh (Standard)",
      "Pompe à chaleur de série sur Long Range, hivers nettement mieux gérés",
      "Garantie constructeur 7 ans / 150 000 km, leader sur le segment"
    ],
    "weaknesses": [
      "Architecture 400 V, pic de charge 128 kW : en retrait des EV6/EV9 (800 V)",
      "Autonomie autoroute Standard limitante (~265 km réels à 130 km/h)",
      "Prix qui grimpe vite avec les options (proche de 50 000 € en GT-Line équipée)",
      "Finition GT-Line indisponible avec batterie Standard, gamme contrainte",
      "Pas de version traction intégrale possible"
    ],
    "idealUserProfile": "Foyer dont elle est l'unique voiture, qui effectue plusieurs trajets longue distance par mois. Le Standard Air à 38 290 € est l'achat le plus accessible ; le Long Range Air à 42 890 € le plus rationnel pour un usage mixte.",
    "notIdealFor": "Conducteur strictement urbain n'ayant jamais besoin de plus de 200 km : la Standard suffit. Voyageurs autoroutiers très fréquents trouveront la charge 400 V en retrait des architectures 800 V."
  },
  "lastUpdated": "2026-05-18",
  "sources": [
    "nyland",
    "insideevs-de",
    "automobile-propre",
    "caradisiac",
    "actua-auto",
    "touring",
    "largus",
    "kia-fr"
  ],
  "imageCredit": "Kia France, visuel presse 2026"
}
