{
  "slug": "renault-grand-kangoo",
  "brand": "Renault",
  "model": "Grand Kangoo E-Tech",
  "variant": "45 kWh",
  "bodyType": "Ludospace 7 places",
  "segment": "D",
  "productionCountry": "France",
  "assemblyPlant": "Maubeuge",
  "releaseYear": 2024,
  "marketAvailability": "Disponible",
  "power_kW": 90,
  "power_hp": 122,
  "torque_Nm": 245,
  "drivetrain": "FWD",
  "motors": 1,
  "acceleration_0_100_s": 13.5,
  "topSpeed_kmh": 132,
  "usableCapacity_kWh": 45,
  "grossCapacity_kWh": 48,
  "chemistry": "NMC",
  "architecture_V": 400,
  "mass_kg": 2050,
  "wltp_max_km": 265,
  "wltp_min_km": 265,
  "realRange": {
    "mixed_km": 200,
    "highway_130_km": 130,
    "urban_km": 250,
    "winter_minus5_km": 160,
    "confidence": "estimated",
    "highway_120_km": 371
  },
  "consumption_mixed_kWh_per_100km": 19.5,
  "consumption_highway_kWh_per_100km": 27,
  "consumption_winter_kWh_per_100km": 23,
  "dragCoefficient_Cx": 0.36,
  "chargingDC": {
    "peakPower_kW": 80,
    "time_10_80_min": 37,
    "kWh_added_30min": 27,
    "confidence": "estimated"
  },
  "chargingAC": {
    "onboardCharger_kW": 22,
    "phases": 3,
    "time_0_100_h": 3
  },
  "plugAndCharge": false,
  "v2l": false,
  "v2g": false,
  "v2l_option_EUR": null,
  "chargingCurve": [
    {
      "soc": 0,
      "power": 62
    },
    {
      "soc": 10,
      "power": 80
    },
    {
      "soc": 50,
      "power": 62
    },
    {
      "soc": 80,
      "power": 31
    },
    {
      "soc": 100,
      "power": 6
    }
  ],
  "rangeTests": [],
  "thousandKmChallenge": {
    "sourceId": "nyland",
    "totalTime_minutes": 610,
    "averageSpeed_kmh": 98.4,
    "averageConsumption_Wh_km": 274,
    "chargingStops": null,
    "averageTemperature_C": 12,
    "testDate": null,
    "videoUrl": null,
    "confidence": "tested"
  },
  "length_mm": 4910,
  "width_mm": 1919,
  "height_mm": 1838,
  "wheelbase_mm": 3100,
  "trunkCapacity_L": 500,
  "trunkCapacityFolded_L": 2800,
  "frunkCapacity_L": null,
  "trims": [
    {
      "name": "Techno",
      "price_EUR": 40500,
      "batteryUsed": "45 kWh",
      "equipmentHighlights": [
        "7 places modulables",
        "OpenR Link Google",
        "Charge AC 22 kW",
        "Portes coulissantes"
      ]
    }
  ],
  "leasingSocialEligible": false,
  "leasingSocial_EUR_per_month": null,
  "availableAids": [
    {
      "label": "Prime CEE",
      "amount_EUR": 6500,
      "conditions": "Socle de base de la Prime CEE 2026 pour véhicule éligible à l'éco-score ADEME."
    },
    {
      "label": "Majoration Batterie Européenne",
      "amount_EUR": 2000,
      "conditions": "Majoration pour batterie fabriquée en Europe."
    }
  ],
  "configurations": [
    {
      "id": "renault-grand-kangoo-techno",
      "label": "Grand Kangoo E-Tech Techno",
      "battery": "standard",
      "trim": "Techno",
      "wheelSize_inches": 16,
      "tyreType": "summer",
      "options": [],
      "price_EUR": 40500,
      "monthlyLease_EUR": null,
      "leasingSocialEligible": false,
      "wltp_km": 265,
      "wltp_consumption_kWh_100km": 19.5,
      "realRange": {
        "mixed_km": 200,
        "highway_130_km": 130,
        "urban_km": 250,
        "winter_minus5_km": 160,
        "confidence": "estimated"
      },
      "rangeTests": [],
      "chargingDC_peak_kW": 80,
      "chargingDC_10_80_min": 37,
      "chargingDC_kWh_30min": 27,
      "chargingCurve": [
        {
          "soc": 0,
          "power": 62
        },
        {
          "soc": 10,
          "power": 80
        },
        {
          "soc": 50,
          "power": 62
        },
        {
          "soc": 80,
          "power": 31
        },
        {
          "soc": 100,
          "power": 6
        }
      ],
      "availability": "available",
      "notes": "122 ch (90 kW). Charge AC 22 kW tri. 7 places."
    }
  ],
  "warranty": {
    "vehicle_years": 5,
    "vehicle_km": 100000,
    "battery_years": 8,
    "battery_km": 160000,
    "battery_soh_minimum_percent": 70
  },
  "keyFeatures": [
    {
      "category": "confort",
      "label": "7 places modulables avec sieges amovibles"
    },
    {
      "category": "technologie",
      "label": "OpenR Link avec Google integre"
    },
    {
      "category": "securite",
      "label": "Freinage automatique d'urgence"
    },
    {
      "category": "design",
      "label": "Portes laterales coulissantes, empattement long"
    }
  ],
  "verdict": {
    "strengths": [
      "Seul ludospace electrique 7 places du marche",
      "Modularite exceptionnelle (sieges amovibles)",
      "Charge AC 22 kW de serie"
    ],
    "weaknesses": [
      "Autonomie limitee pour un vehicule familial (265 km WLTP)",
      "Charge DC plafonnee a 80 kW",
      "Masse elevee impactant la consommation"
    ],
    "idealUserProfile": "Grandes familles cherchant un vehicule 7 places electrique pour les trajets quotidiens.",
    "notIdealFor": "Gros rouleurs autoroutiers ou departs en vacances longue distance frequents."
  },
  "lastUpdated": "2026-05-29",
  "sources": [
    "la-chaine-ev",
    "nyland"
  ],
  "imageCredit": "Constructeur"
}
